napari_timestamper/__init__.py
napari_timestamper/_layer_annotator_overlay.py
napari_timestamper/_timestamp_overlay.py
napari_timestamper/_version.py
napari_timestamper/_widget.py
napari_timestamper/napari.yaml
napari_timestamper/render_as_rgb.py
napari_timestamper/text_visual.py
napari_timestamper/utils.py
napari_timestamper/_tests/__init__.py
napari_timestamper/_tests/test_layer_annotator_overlay.py
napari_timestamper/_tests/test_render_as_rgb.py
napari_timestamper/_tests/test_timestamp_overlay.py
napari_timestamper/_tests/test_widget.py
napari_timestamper-0.5.0.dist-info/licenses/LICENSE
napari_timestamper-0.5.0.dist-info/METADATA
napari_timestamper-0.5.0.dist-info/WHEEL
napari_timestamper-0.5.0.dist-info/entry_points.txt
napari_timestamper-0.5.0.dist-info/top_level.txt
napari_timestamper-0.5.0.dist-info/RECORD
