Metadata-Version: 2.4
Name: napari-timestamper
Version: 0.5.0
Summary: A simple plugin to add a timestamp overlay to napari
Home-page: https://github.com/bgraedel/napari-timestamper
Author: Benjamin Grädel
Author-email: benjamin.graedel@unibe.ch
License: BSD-3-Clause
Project-URL: Bug Tracker, https://github.com/bgraedel/napari-timestamper/issues
Project-URL: Documentation, https://github.com/bgraedel/napari-timestamper#README.md
Project-URL: Source Code, https://github.com/bgraedel/napari-timestamper
Project-URL: User Support, https://github.com/bgraedel/napari-timestamper/issues
Classifier: Development Status :: 2 - Pre-Alpha
Classifier: Intended Audience :: Developers
Classifier: License :: OSI Approved :: BSD License
Classifier: Operating System :: OS Independent
Classifier: Programming Language :: Python
Classifier: Programming Language :: Python :: 3
Classifier: Programming Language :: Python :: 3 :: Only
Classifier: Programming Language :: Python :: 3.9
Classifier: Programming Language :: Python :: 3.10
Classifier: Programming Language :: Python :: 3.11
Classifier: Programming Language :: Python :: 3.12
Classifier: Programming Language :: Python :: 3.13
Classifier: Topic :: Scientific/Engineering :: Image Processing
Requires-Python: >=3.9
License-File: LICENSE
Requires-Dist: numpy
Requires-Dist: qtpy
Provides-Extra: testing
Requires-Dist: tox; extra == "testing"
Requires-Dist: pytest; extra == "testing"
Requires-Dist: pytest-cov; extra == "testing"
Requires-Dist: pytest-qt; extra == "testing"
Requires-Dist: napari>=0.5.0; extra == "testing"
Requires-Dist: pyqt5; extra == "testing"
Dynamic: license-file
